twoHalfAdders/twoHalfAdders.v
module twoHalfAdders (
    input a, b, cin,
    output sum, carry
);
wire sum1, carry1, carry2;
assign sum1 = a^b;
assign carry1 = a&b;
assign sum = sum1^cin;
assign carry2 = sum1&cin;
assign carry = carry1|carry2;
endmodule

twoHalfAdders/twoHalfAddersTest.v
module twoHalfAddersTest;
reg a, b, cin;
wire sum, carry;
twoHalfAdders uut (
    .a(a), .b(b), .cin(cin), .sum(sum), .carry(carry)
);
initial begin
a=0; b=0; cin=0; #10;
a=0; b=0; cin=1; #10;
a=0; b=1; cin=0; #10;
a=0; b=1; cin=1; #10;
a=1; b=0; cin=0; #10;
a=1; b=0; cin=1; #10;
a=1; b=1; cin=0; #10;
a=1; b=1; cin=1; #10;
$finish;
end
initial begin
$monitor("Time=%0d, a=%b, b=%b, cin=%b, carry1=%b, carry2=%b, carry=%b, sum1=%b, sum=%b", $time, a, b, cin, uut.carry1, uut.carry2, carry, uut.sum1, sum);
end
initial begin
    $dumpfile("twoHalfAdders.vcd");
    $dumpvars(0,twoHalfAddersTest);
end
endmodule

twoHalfAdders/twoHalfAdders.vcd
$date
	Sat Jul 25 13:29:42 2026
$end
$version
	Icarus Verilog
$end
$timescale
	1s
$end
$scope module twoHalfAddersTest $end
$var wire 1 ! sum $end
$var wire 1 " carry $end
$var reg 1 # a $end
$var reg 1 $ b $end
$var reg 1 % cin $end
$scope module uut $end
$var wire 1 # a $end
$var wire 1 $ b $end
$var wire 1 " carry $end
$var wire 1 & carry1 $end
$var wire 1 ' carry2 $end
$var wire 1 % cin $end
$var wire 1 ! sum $end
$var wire 1 ( sum1 $end
$upscope $end
$upscope $end
$enddefinitions $end
$comment Show the parameter values. $end
$dumpall
$end
#0
$dumpvars
0(
0'
0&
0%
0$
0#
0"
0!
$end
#10
1!
1%
#20
1(
0%
1$
#30
1"
0!
1'
1%
#40
0"
1!
0'
0%
0$
1#
#50
1"
0!
1'
1%
#60
0'
0(
1&
0%
1$
#70
1!
1%
