full_adder/or.v
module Or (
    input a, b,
    output Or
);
assign Or = a|b;
endmodule

full_adder/and.v
module And (
input a, b,
output And
);
assign And = a&b;
endmodule

full_adder/xor.v
module Xor (
input a, b, output Xor
);
assign Xor = a^b;
endmodule

full_adder/half_adder.v
module half_adder (
input a, b,
output sum, carry
);
Xor x1 (
    .a(a),
    .b(b),
    .Xor(sum)
);
And x2 (
    .a(a),
    .b(b),
    .And(carry)
);
endmodule

full_adder/full_adder.v
module full_adder (
    input a, b, cin,
    output sum, carry
);

wire c1, c2, s1;

half_adder h1 (
    .a(a),
    .b(b),
    .sum(s1),
    .carry(c1)
);

half_adder h2 (
    .a(s1),
    .b(cin),
    .sum(sum),
    .carry(c2)
);

Or x3 (
    .a(c1),
    .b(c2),
    .Or(carry)
);

endmodule

full_adder/full_adder_tb.v
module full_adder_tb;
reg a, b, cin;
wire sum, carry;
full_adder uut (
    .a(a), .b(b), .cin(cin), .sum(sum), .carry(carry)
);
initial begin
a=0; b=0; cin=0; #10;
a=0; b=0; cin=1; #10;
a=0; b=1; cin=0; #10;
a=0; b=1; cin=1; #10;
a=1; b=0; cin=0; #10;
a=1; b=0; cin=1; #10;
a=1; b=1; cin=0; #10;
a=1; b=1; cin=1; #10;
$finish;
end
initial begin
$monitor("Time=%0d, a=%b, b=%b, cin=%b, carry1=%b, carry2=%b, carry=%b, sum1=%b, sum=%b",
$time, a, b, cin, uut.c1, uut.c2, carry, uut.s1, sum);
end
initial begin
    $dumpfile("full_adder.vcd");
    $dumpvars(0,full_adder_tb);
end
endmodule

full_adder/full_adder.vcd
$date
	Sun Jul 26 13:45:39 2026
$end
$version
	Icarus Verilog
$end
$timescale
	1s
$end
$scope module full_adder_tb $end
$var wire 1 ! sum $end
$var wire 1 " carry $end
$var reg 1 # a $end
$var reg 1 $ b $end
$var reg 1 % cin $end
$scope module uut $end
$var wire 1 # a $end
$var wire 1 $ b $end
$var wire 1 % cin $end
$var wire 1 ! sum $end
$var wire 1 & s1 $end
$var wire 1 " carry $end
$var wire 1 ' c2 $end
$var wire 1 ( c1 $end
$scope module h1 $end
$var wire 1 # a $end
$var wire 1 $ b $end
$var wire 1 & sum $end
$var wire 1 ( carry $end
$scope module x1 $end
$var wire 1 & Xor $end
$var wire 1 # a $end
$var wire 1 $ b $end
$upscope $end
$scope module x2 $end
$var wire 1 ( And $end
$var wire 1 # a $end
$var wire 1 $ b $end
$upscope $end
$upscope $end
$scope module h2 $end
$var wire 1 & a $end
$var wire 1 % b $end
$var wire 1 ! sum $end
$var wire 1 ' carry $end
$scope module x1 $end
$var wire 1 ! Xor $end
$var wire 1 & a $end
$var wire 1 % b $end
$upscope $end
$scope module x2 $end
$var wire 1 ' And $end
$var wire 1 & a $end
$var wire 1 % b $end
$upscope $end
$upscope $end
$scope module x3 $end
$var wire 1 " Or $end
$var wire 1 ( a $end
$var wire 1 ' b $end
$upscope $end
$upscope $end
$upscope $end
$enddefinitions $end
$comment Show the parameter values. $end
$dumpall
$end
#0
$dumpvars
0(
0'
0&
0%
0$
0#
0"
0!
$end
#10
1!
1%
#20
1&
0%
1$
#30
1"
0!
1'
1%
#40
0"
1!
0'
0%
0$
1#
#50
1"
0!
1'
1%
#60
0'
0&
1(
0%
1$
#70
1!
1%
